claude_task_master/__init__.py
claude_task_master/cli.py
claude_task_master/server.py
claude_task_master/wrapper.py
claude_task_master/api/__init__.py
claude_task_master/api/models.py
claude_task_master/api/routes.py
claude_task_master/api/routes_config.py
claude_task_master/api/routes_control.py
claude_task_master/api/routes_repo.py
claude_task_master/api/routes_webhooks.py
claude_task_master/api/server.py
claude_task_master/auth/__init__.py
claude_task_master/auth/middleware.py
claude_task_master/auth/password.py
claude_task_master/bin/claudetm
claude_task_master/cli_commands/__init__.py
claude_task_master/cli_commands/ci_helpers.py
claude_task_master/cli_commands/config.py
claude_task_master/cli_commands/control.py
claude_task_master/cli_commands/fix_pr.py
claude_task_master/cli_commands/fix_session.py
claude_task_master/cli_commands/github.py
claude_task_master/cli_commands/info.py
claude_task_master/cli_commands/mailbox.py
claude_task_master/cli_commands/workflow.py
claude_task_master/core/__init__.py
claude_task_master/core/agent.py
claude_task_master/core/agent_exceptions.py
claude_task_master/core/agent_message.py
claude_task_master/core/agent_models.py
claude_task_master/core/agent_phases.py
claude_task_master/core/agent_query.py
claude_task_master/core/checkpoint.py
claude_task_master/core/circuit_breaker.py
claude_task_master/core/config.py
claude_task_master/core/config_loader.py
claude_task_master/core/console.py
claude_task_master/core/context_accumulator.py
claude_task_master/core/control.py
claude_task_master/core/conversation.py
claude_task_master/core/credentials.py
claude_task_master/core/hooks.py
claude_task_master/core/key_listener.py
claude_task_master/core/logger.py
claude_task_master/core/orchestrator.py
claude_task_master/core/parallel.py
claude_task_master/core/plan_updater.py
claude_task_master/core/planner.py
claude_task_master/core/pr_context.py
claude_task_master/core/progress_tracker.py
claude_task_master/core/prompts.py
claude_task_master-0.1.8.dist-info/METADATA
claude_task_master-0.1.8.dist-info/WHEEL
claude_task_master-0.1.8.dist-info/entry_points.txt
claude_task_master-0.1.8.dist-info/top_level.txt
claude_task_master-0.1.8.dist-info/RECORD
