Metadata-Version: 2.4
Name: claude-task-master
Version: 0.1.8
Summary: Autonomous task orchestration system that keeps Claude working until a goal is achieved
Author: Claude Task Master Team
License-Expression: MIT
Project-URL: Homepage, https://github.com/developerz-ai/claude-task-master
Project-URL: Documentation, https://github.com/developerz-ai/claude-task-master#readme
Project-URL: Repository, https://github.com/developerz-ai/claude-task-master
Project-URL: Issues, https://github.com/developerz-ai/claude-task-master/issues
Project-URL: Changelog, https://github.com/developerz-ai/claude-task-master/blob/main/CHANGELOG.md
Keywords: claude,agent,autonomous,task,orchestration,ai,automation
Classifier: Development Status :: 3 - Alpha
Classifier: Intended Audience :: Developers
Classifier: Programming Language :: Python :: 3
Classifier: Programming Language :: Python :: 3.12
Classifier: Operating System :: OS Independent
Classifier: Topic :: Software Development :: Libraries :: Python Modules
Classifier: Topic :: Scientific/Engineering :: Artificial Intelligence
Requires-Python: >=3.12
Requires-Dist: claude-agent-sdk>=0.1.0
Requires-Dist: typer>=0.12.0
Requires-Dist: pydantic>=2.0.0
Requires-Dist: rich>=13.0.0
Requires-Dist: httpx>=0.27.0
Provides-Extra: mcp
Requires-Dist: mcp>=1.0.0; extra == "mcp"
Provides-Extra: api
Requires-Dist: fastapi>=0.100.0; extra == "api"
Requires-Dist: uvicorn[standard]>=0.24.0; extra == "api"
Requires-Dist: passlib[bcrypt]>=1.7.4; extra == "api"
Requires-Dist: bcrypt<4.1.0,>=4.0.0; extra == "api"
Provides-Extra: dev
Requires-Dist: claude-task-master[api]; extra == "dev"
Requires-Dist: pytest>=8.0.0; extra == "dev"
Requires-Dist: pytest-cov>=4.1.0; extra == "dev"
Requires-Dist: pytest-asyncio>=0.23.0; extra == "dev"
Requires-Dist: pytest-timeout>=2.4.0; extra == "dev"
Requires-Dist: hypothesis>=6.100.0; extra == "dev"
Requires-Dist: ruff>=0.3.0; extra == "dev"
Requires-Dist: mypy>=1.9.0; extra == "dev"
Provides-Extra: all
Requires-Dist: claude-task-master[api,dev,mcp]; extra == "all"
